precious_lotr_sdk/__init__.py
precious_lotr_sdk/lotr.py
precious_lotr_sdk-1.0.2.dist-info/METADATA
precious_lotr_sdk-1.0.2.dist-info/WHEEL
precious_lotr_sdk-1.0.2.dist-info/top_level.txt
precious_lotr_sdk-1.0.2.dist-info/RECORD
