Metadata-Version: 2.1
Name: precious-lotr-sdk
Version: 1.0.2
Summary: Python SDK for The Lord of the Rings API
Home-page: UNKNOWN
Author: Suhaib Alfageeh
Author-email: suhaib@alfadesigned.com
License: UNKNOWN
Platform: UNKNOWN
Requires-Dist: requests
